nwtools/__init__.py
nwtools/cli.py
nwtools/core.py
nwtools/simple_tui.py
nwtools/stable_tui.py
nwtools/tui.py
nwtools/utils.py
nwtools-3.0.0.dist-info/METADATA
nwtools-3.0.0.dist-info/WHEEL
nwtools-3.0.0.dist-info/entry_points.txt
nwtools-3.0.0.dist-info/top_level.txt
nwtools-3.0.0.dist-info/RECORD
